GenWoYiqiXieBianyiqiFix1/README.md
GenWoYiqiXieBianyiqiFix1/__init__.py
GenWoYiqiXieBianyiqiFix1/__main__.py
GenWoYiqiXieBianyiqiFix1/file.epub
GenWoYiqiXieBianyiqiFix1/index.html
GenWoYiqiXieBianyiqiFix1/css/__init__.py
GenWoYiqiXieBianyiqiFix1/css/annotations.css
GenWoYiqiXieBianyiqiFix1/css/main.css
GenWoYiqiXieBianyiqiFix1/css/normalize.css
GenWoYiqiXieBianyiqiFix1/css/popup.css
GenWoYiqiXieBianyiqiFix1/font/__init__.py
GenWoYiqiXieBianyiqiFix1/font/fontello.eot
GenWoYiqiXieBianyiqiFix1/font/fontello.svg
GenWoYiqiXieBianyiqiFix1/font/fontello.ttf
GenWoYiqiXieBianyiqiFix1/font/fontello.woff
GenWoYiqiXieBianyiqiFix1/img/__init__.py
GenWoYiqiXieBianyiqiFix1/img/annotator-glyph-sprite.png
GenWoYiqiXieBianyiqiFix1/img/annotator-icon-sprite.png
GenWoYiqiXieBianyiqiFix1/img/apple-touch-icon.png
GenWoYiqiXieBianyiqiFix1/img/cancelfullscreen.png
GenWoYiqiXieBianyiqiFix1/img/close.png
GenWoYiqiXieBianyiqiFix1/img/fullscreen.png
GenWoYiqiXieBianyiqiFix1/img/loader.gif
GenWoYiqiXieBianyiqiFix1/img/menu-icon.png
GenWoYiqiXieBianyiqiFix1/img/save.png
GenWoYiqiXieBianyiqiFix1/img/saved.png
GenWoYiqiXieBianyiqiFix1/img/settings-s.png
GenWoYiqiXieBianyiqiFix1/img/settings.png
GenWoYiqiXieBianyiqiFix1/img/star.png
GenWoYiqiXieBianyiqiFix1/js/__init__.py
GenWoYiqiXieBianyiqiFix1/js/epub.js
GenWoYiqiXieBianyiqiFix1/js/epub.min.js
GenWoYiqiXieBianyiqiFix1/js/epub.min.map
GenWoYiqiXieBianyiqiFix1/js/hooks.min.js
GenWoYiqiXieBianyiqiFix1/js/hooks.min.map
GenWoYiqiXieBianyiqiFix1/js/reader.js
GenWoYiqiXieBianyiqiFix1/js/reader.js.map
GenWoYiqiXieBianyiqiFix1/js/reader.min.js
GenWoYiqiXieBianyiqiFix1/js/reader.min.map
GenWoYiqiXieBianyiqiFix1/js/hooks/__init__.py
GenWoYiqiXieBianyiqiFix1/js/hooks/extensions/__init__.py
GenWoYiqiXieBianyiqiFix1/js/hooks/extensions/highlight.js
GenWoYiqiXieBianyiqiFix1/js/libs/__init__.py
GenWoYiqiXieBianyiqiFix1/js/libs/jquery.min.js
GenWoYiqiXieBianyiqiFix1/js/libs/localforage.min.js
GenWoYiqiXieBianyiqiFix1/js/libs/screenfull.js
gen_wo_yiqi_xie_bianyiqi_fix1-2025.3.25.0.dist-info/METADATA
gen_wo_yiqi_xie_bianyiqi_fix1-2025.3.25.0.dist-info/WHEEL
gen_wo_yiqi_xie_bianyiqi_fix1-2025.3.25.0.dist-info/entry_points.txt
gen_wo_yiqi_xie_bianyiqi_fix1-2025.3.25.0.dist-info/top_level.txt
gen_wo_yiqi_xie_bianyiqi_fix1-2025.3.25.0.dist-info/RECORD
